{"B Laughlin": {"strike_rate": 0, "runs": 0, "balls_faced": 0}, "B Stanlake": {"strike_rate": 0, "runs": 0, "balls_faced": 0}, "J Dean": {"strike_rate": 0.0, "runs": 0, "balls_faced": 1}, "B Hodge": {"strike_rate": 142.10526315789474, "runs": 54, "balls_faced": 38}, "K Smith": {"strike_rate": 0, "runs": 0, "balls_faced": 0}, "J Weatherald": {"strike_rate": 115.38461538461537, "runs": 75, "balls_faced": 65}, "C Jordan": {"strike_rate": 0, "runs": 0, "balls_faced": 0}, "K Richardson": {"strike_rate": 0, "runs": 0, "balls_faced": 0}, "A Carey": {"strike_rate": 0, "runs": 0, "balls_faced": 0}, "M Neser": {"strike_rate": 0, "runs": 0, "balls_faced": 0}, "A Rashid": {"strike_rate": 0, "runs": 0, "balls_faced": 0}, "T Ludeman": {"strike_rate": 122.50000000000001, "runs": 49, "balls_faced": 40}, "W Agar": {"strike_rate": 0, "runs": 0, "balls_faced": 0}, "K Pollard": {"strike_rate": 100.0, "runs": 2, "balls_faced": 2}, "J Lehmann": {"strike_rate": 0, "runs": 0, "balls_faced": 0}, "C Simmons": {"strike_rate": 0, "runs": 0, "balls_faced": 0}, "J Holland": {"strike_rate": 0, "runs": 0, "balls_faced": 0}, "T Head": {"strike_rate": 95.83333333333334, "runs": 23, "balls_faced": 24}, "B Dunk": {"strike_rate": 173.17073170731706, "runs": 213, "balls_faced": 123}}